rakuten_recipe_scraping-0.1.0.dist-info/licenses/LICENSE
rakutenrecipescraping/__init__.py
rakutenrecipescraping/scraping.py
rakuten_recipe_scraping-0.1.0.dist-info/METADATA
rakuten_recipe_scraping-0.1.0.dist-info/WHEEL
rakuten_recipe_scraping-0.1.0.dist-info/top_level.txt
rakuten_recipe_scraping-0.1.0.dist-info/RECORD
