Metadata-Version: 2.4
Name: rakuten_recipe_scraping
Version: 0.1.0
Summary: 楽天レシピのデータをスクレイピングするためのライブラリ
Home-page: https://github.com/gesouni/rakuten_recipe_scraping
Author: gesouni
Author-email: w5eq4hgv7q6y@gmail.com
Classifier: Programming Language :: Python :: 3
Classifier: Operating System :: OS Independent
Requires-Python: >=3.7
License-File: LICENSE
Requires-Dist: requests
Requires-Dist: beautifulsoup4
Dynamic: author
Dynamic: author-email
Dynamic: classifier
Dynamic: description
Dynamic: description-content-type
Dynamic: home-page
Dynamic: license-file
Dynamic: requires-dist
Dynamic: requires-python
Dynamic: summary
